CHANGES.txt
DEPENDENCES.txt
README.txt
setup.py
design/index.html
design/style.css
design/images/animal.jpg
design/images/author.jpg
design/images/leftslotbg.gif
design/images/listitem.gif
design/images/logo.gif
design/images/logo.jpg
design/images/member1.jpg
design/images/member2.jpg
design/images/menubg.gif
src/ng/__init__.py
src/ng.skin.greenpsy.egg-info/PKG-INFO
src/ng.skin.greenpsy.egg-info/SOURCES.txt
src/ng.skin.greenpsy.egg-info/dependency_links.txt
src/ng.skin.greenpsy.egg-info/namespace_packages.txt
src/ng.skin.greenpsy.egg-info/not-zip-safe
src/ng.skin.greenpsy.egg-info/requires.txt
src/ng.skin.greenpsy.egg-info/top_level.txt
src/ng/skin/__init__.py
src/ng/skin/greenpsy/__init__.py
src/ng/skin/greenpsy/configure.zcml
src/ng/skin/greenpsy/interfaces.py
src/ng/skin/greenpsy/ng.skin.greenpsy.txt
src/ng/skin/greenpsy/orderinformation.py
src/ng/skin/greenpsy/skeleton.pt
src/ng/skin/greenpsy/style.css
src/ng/skin/greenpsy/style_form.css
src/ng/skin/greenpsy/style_ie.css
src/ng/skin/greenpsy/style_print.css
src/ng/skin/greenpsy/etc/ng.skin.greenpsy-configure.zcml
src/ng/skin/greenpsy/images/animal.jpg
src/ng/skin/greenpsy/images/ecoschool.jpg
src/ng/skin/greenpsy/images/headerbg.gif
src/ng/skin/greenpsy/images/headerbg.jpg
src/ng/skin/greenpsy/images/logo.gif
src/ng/skin/greenpsy/images/logo.jpg
src/ng/skin/greenpsy/images/logo.png
src/ng/skin/greenpsy/images/member1.jpg
src/ng/skin/greenpsy/images/member2.jpg
src/ng/skin/greenpsy/images/nophoto-big.gif
src/ng/skin/greenpsy/images/nophoto-small.gif
src/ng/skin/greenpsy/images/title.gif
src/ng/skin/greenpsy/page/__init__.py
src/ng/skin/greenpsy/page/configure.zcml
src/ng/skin/greenpsy/page/add/__init__.py
src/ng/skin/greenpsy/page/add/configure.zcml
src/ng/skin/greenpsy/page/add/dictionaryitem.pt
src/ng/skin/greenpsy/page/addcommunity/__init__.py
src/ng/skin/greenpsy/page/addcommunity/addcommunity.py
src/ng/skin/greenpsy/page/addcommunity/configure.zcml
src/ng/skin/greenpsy/page/chat/__init__.py
src/ng/skin/greenpsy/page/chat/chat.pt
src/ng/skin/greenpsy/page/chat/chat.py
src/ng/skin/greenpsy/page/chat/configure.zcml
src/ng/skin/greenpsy/page/commonedit/__init__.py
src/ng/skin/greenpsy/page/commonedit/configure.zcml
src/ng/skin/greenpsy/page/communitychoice/__init__.py
